openhab_mcp_server/__init__.py
openhab_mcp_server/__main__.py
openhab_mcp_server/cli.py
openhab_mcp_server/models.py
openhab_mcp_server/py.typed
openhab_mcp_server/server.py
openhab_mcp_server/resources/__init__.py
openhab_mcp_server/resources/openhab.py
openhab_mcp_server/tools/__init__.py
openhab_mcp_server/tools/addons.py
openhab_mcp_server/tools/examples.py
openhab_mcp_server/tools/items.py
openhab_mcp_server/tools/links.py
openhab_mcp_server/tools/rules.py
openhab_mcp_server/tools/scripts.py
openhab_mcp_server/tools/things.py
openhab_mcp_server/tools/transformations.py
openhab_mcp_server/tools/ui.py
openhab_mcp_server/utils/__init__.py
openhab_mcp_server/utils/config.py
openhab_mcp_server/utils/diagnostics.py
openhab_mcp_server/utils/health.py
openhab_mcp_server/utils/logging.py
openhab_mcp_server/utils/openhab_client.py
openhab_mcp_server/utils/script_context.py
openhab_mcp_server/utils/script_sandbox.py
openhab_mcp_server/utils/security.py
openhab_mcp_server-1.1.1.dist-info/licenses/LICENSE
openhab_mcp_server-1.1.1.dist-info/METADATA
openhab_mcp_server-1.1.1.dist-info/WHEEL
openhab_mcp_server-1.1.1.dist-info/entry_points.txt
openhab_mcp_server-1.1.1.dist-info/top_level.txt
openhab_mcp_server-1.1.1.dist-info/RECORD
