Metadata-Version: 2.4
Name: openhab-mcp-server
Version: 1.1.1
Summary: Model Context Protocol server for openHAB home automation
Author-email: openHAB MCP Server Contributors <info@example.com>
Maintainer-email: openHAB MCP Server Contributors <info@example.com>
License-Expression: MIT
Project-URL: Homepage, https://github.com/openhab/openhab-mcp-server
Project-URL: Documentation, https://github.com/openhab/openhab-mcp-server#readme
Project-URL: Repository, https://github.com/openhab/openhab-mcp-server.git
Project-URL: Issues, https://github.com/openhab/openhab-mcp-server/issues
Project-URL: Changelog, https://github.com/openhab/openhab-mcp-server/blob/main/CHANGELOG.md
Keywords: openhab,mcp,model-context-protocol,home-automation,ai-assistant,smart-home,iot
Classifier: Development Status :: 4 - Beta
Classifier: Intended Audience :: Developers
Classifier: Intended Audience :: End Users/Desktop
Classifier: Operating System :: OS Independent
Classifier: Programming Language :: Python :: 3
Classifier: Programming Language :: Python :: 3.8
Classifier: Programming Language :: Python :: 3.9
Classifier: Programming Language :: Python :: 3.10
Classifier: Programming Language :: Python :: 3.11
Classifier: Programming Language :: Python :: 3.12
Classifier: Topic :: Home Automation
Classifier: Topic :: Software Development :: Libraries :: Python Modules
Classifier: Topic :: System :: Hardware
Classifier: Topic :: Communications
Classifier: Typing :: Typed
Requires-Python: >=3.8
License-File: LICENSE
Requires-Dist: mcp>=1.0.0
Requires-Dist: aiohttp>=3.8.0
Requires-Dist: pydantic>=2.0.0
Provides-Extra: dev
Requires-Dist: pytest>=7.0.0; extra == "dev"
Requires-Dist: pytest-asyncio>=0.21.0; extra == "dev"
Requires-Dist: aioresponses>=0.7.4; extra == "dev"
Requires-Dist: hypothesis>=6.0.0; extra == "dev"
Requires-Dist: black>=23.0.0; extra == "dev"
Requires-Dist: ruff>=0.1.0; extra == "dev"
Requires-Dist: mypy>=1.0.0; extra == "dev"
Provides-Extra: test
Requires-Dist: pytest>=7.0.0; extra == "test"
Requires-Dist: pytest-asyncio>=0.21.0; extra == "test"
Requires-Dist: aioresponses>=0.7.4; extra == "test"
Requires-Dist: hypothesis>=6.0.0; extra == "test"
Provides-Extra: lint
Requires-Dist: black>=23.0.0; extra == "lint"
Requires-Dist: ruff>=0.1.0; extra == "lint"
Requires-Dist: mypy>=1.0.0; extra == "lint"
Dynamic: license-file
